README.md
pyproject.toml
setup.cfg
src/pycliutils/__init__.py
src/pycliutils/py.typed
src/pycliutils.egg-info/PKG-INFO
src/pycliutils.egg-info/SOURCES.txt
src/pycliutils.egg-info/dependency_links.txt
src/pycliutils.egg-info/requires.txt
src/pycliutils.egg-info/top_level.txt
src/pycliutils/args/__init__.py
src/pycliutils/args/config.py
src/pycliutils/args/formatter.py
src/pycliutils/args/parser.py
src/pycliutils/fmt/__init__.py
src/pycliutils/fmt/const.py
src/pycliutils/fmt/text.py
src/pycliutils/tty/__init__.py
src/pycliutils/tty/config.py
src/pycliutils/tty/interactive.py
src/pycliutils/tty/out.py
src/pycliutils/tty/inpt/__init__.py
src/pycliutils/tty/inpt/selector.py
src/pycliutils/tty/inpt/unix.py
src/pycliutils/validators/__init__.py
src/pycliutils/validators/number.py
src/pycliutils/validators/path.py
src/pycliutils/validators/selector.py
src/pycliutils/validators/validator.py